dash_socketio/DashSocketIO.py
dash_socketio/__init__.py
dash_socketio/_imports_.py
dash_socketio/dash_socketio.js
dash_socketio/metadata.json
dash_socketio/package-info.json
dash_socketio-1.1.1.dist-info/METADATA
dash_socketio-1.1.1.dist-info/WHEEL
dash_socketio-1.1.1.dist-info/top_level.txt
dash_socketio-1.1.1.dist-info/RECORD
