Metadata-Version: 2.2
Name: dash_socketio
Version: 1.1.1
Summary: Client Socket.IO for Dash
Author: Renaud Lainé <>
License: MIT
Classifier: Framework :: Dash
Dynamic: author
Dynamic: classifier
Dynamic: description
Dynamic: description-content-type
Dynamic: license
Dynamic: summary
